llama_index/packs/fusion_retriever/__init__.py
llama_index/packs/fusion_retriever/hybrid_fusion/__init__.py
llama_index/packs/fusion_retriever/hybrid_fusion/base.py
llama_index/packs/fusion_retriever/query_rewrite/__init__.py
llama_index/packs/fusion_retriever/query_rewrite/base.py
llama_index_packs_fusion_retriever-0.5.1.dist-info/METADATA
llama_index_packs_fusion_retriever-0.5.1.dist-info/WHEEL
llama_index_packs_fusion_retriever-0.5.1.dist-info/licenses/LICENSE
llama_index_packs_fusion_retriever-0.5.1.dist-info/RECORD
