Metadata-Version: 2.4
Name: llama-index-packs-fusion-retriever
Version: 0.5.1
Summary: llama-index packs fusion_retriever integration
Author-email: Your Name <you@example.com>
Maintainer: jerryjliu
License-Expression: MIT
License-File: LICENSE
Keywords: fusion,hybrid,query,retriever,rewriting
Requires-Python: <4.0,>=3.9
Requires-Dist: llama-index-core<0.15,>=0.13.0
Requires-Dist: llama-index-retrievers-bm25<0.7,>=0.6.0
Requires-Dist: rank-bm25<0.3,>=0.2.2
